faenet/__init__.py
faenet/base_model.py
faenet/embedding.py
faenet/eval.py
faenet/fa_forward.py
faenet/force_decoder.py
faenet/frame_averaging.py
faenet/model.py
faenet/transforms.py
faenet/utils.py
faenet-0.1.3.dist-info/LICENSE.md
faenet-0.1.3.dist-info/WHEEL
faenet-0.1.3.dist-info/METADATA
faenet-0.1.3.dist-info/RECORD
