Metadata-Version: 2.1
Name: faenet
Version: 0.1.3
Summary: PyTorch implementation for FAENet from 'FAENet: Frame Averaging Equivariant GNN for Materials Modeling'
License: MIT
Author: Victor Schmidt
Author-email: vsch@pm.me
Requires-Python: >=3.8
Classifier: License :: OSI Approved :: MIT License
Classifier: Programming Language :: Python :: 3
Classifier: Programming Language :: Python :: 3.8
Classifier: Programming Language :: Python :: 3.9
Classifier: Programming Language :: Python :: 3.10
Classifier: Programming Language :: Python :: 3.11
Requires-Dist: mendeleev (>=0.12)
Requires-Dist: torch (>=1.12)
